Workbook

Sheet Cards
A1: Era | B1: Region | C1: Name | D1: Epithet | E1: Scale | F1: Wealth | G1: Culture | H1: Knowledge | I1: Might | J1: Tagline
A2: ancient | B2: EU | C2: Rome | D2: Imperial | E2: 97 | F2: 90 | G2: 88 | H2: 80 | I2: 99 | J2: A million souls; all roads lead here.
A3: ancient | B3: EU | C3: Athens | D3: Classical | E3: 60 | F3: 68 | G3: 96 | H3: 98 | I3: 72 | J3: Philosophy, drama, and democracy from one harbor town.
A4: ancient | B4: EU | C4: Syracuse | D4: Greek Sicily | E4: 58 | F4: 72 | G4: 78 | H4: 84 | I4: 74 | J4: Archimedes' hometown — rich, brilliant, hard to besiege.
A5: ancient | B5: EA | C5: Chang'an | D5: Han | E5: 88 | F5: 80 | G5: 76 | H5: 80 | I5: 92 | J5: Eastern terminus of the Silk Road.
A6: ancient | B6: EA | C6: Luoyang | D6: Han | E6: 80 | F6: 72 | G6: 74 | H6: 80 | I6: 84 | J6: Nine dynasties called it capital.
A7: ancient | B7: SA | C7: Pataliputra | D7: Mauryan | E7: 90 | F7: 80 | G7: 74 | H7: 84 | I7: 92 | J7: Ashoka's seat — among the largest cities on Earth.
A8: ancient | B8: SA | C8: Anuradhapura | D8: Sinhalese | E8: 62 | F8: 64 | G8: 72 | H8: 76 | I8: 66 | J8: Sacred stupas and vast reservoir engineering.
A9: ancient | B9: ME | C9: Alexandria | D9: Ptolemaic | E9: 86 | F9: 86 | G9: 88 | H9: 99 | I9: 74 | J9: The Library, the Lighthouse, the world's knowledge.
A10: ancient | B10: ME | C10: Babylon | D10: Neo-Babylonian | E10: 84 | F10: 80 | G10: 84 | H10: 86 | I10: 86 | J10: Hanging gardens, astronomy, the first metropolis.
A11: ancient | B11: ME | C11: Carthage | D11: Punic | E11: 76 | F11: 93 | G11: 72 | H11: 68 | I11: 86 | J11: Merchant empire that nearly broke Rome.
A12: ancient | B12: ME | C12: Persepolis | D12: Achaemenid | E12: 55 | F12: 86 | G12: 82 | H12: 70 | I12: 93 | J12: Ceremonial heart of the first world empire.
A13: ancient | B13: AM | C13: Teotihuacan | D13: Classic | E13: 82 | F13: 72 | G13: 82 | H13: 72 | I13: 86 | J13: The Avenue of the Dead, planned on a grand grid.
... A249: contemporary | B249: AF | C249: Addis Ababa | D249: Hub | E249: 80 | F249: 58 | G249: 62 | H249: 56 | I249: 68 | J249: The AU's capital; an aviation crossroads.

Sheet PoolSizes
A1: Cards per era x region (keep every cell >= 4)
B2: EU | C2: EA | D2: SA | E2: ME | F2: AF | G2: AM
A3: ancient | B3: =COUNTIFS(Cards!$A$2:$A$249,$A3,Cards!$B$2:$B$249,B$2) -> 5 | C3: =COUNTIFS(Cards!$A$2:$A$249,$A3,Cards!$B$2:$B$249,C$2) -> 4 | D3: =COUNTIFS(Cards!$A$2:$A$249,$A3,Cards!$B$2:$B$249,D$2) -> 4 | E3: =COUNTIFS(Cards!$A$2:$A$249,$A3,Cards!$B$2:$B$249,E$2) -> 6 | F3: =COUNTIFS(Cards!$A$2:$A$249,$A3,Cards!$B$2:$B$249,F$2) -> 4 | G3: =COUNTIFS(Cards!$A$2:$A$249,$A3,Cards!$B$2:$B$249,G$2) -> 4
A4: medieval | B4: =COUNTIFS(Cards!$A$2:$A$249,$A4,Cards!$B$2:$B$249,B$2) -> 7 | C4: =COUNTIFS(Cards!$A$2:$A$249,$A4,Cards!$B$2:$B$249,C$2) -> 5 | D4: =COUNTIFS(Cards!$A$2:$A$249,$A4,Cards!$B$2:$B$249,D$2) -> 4 | E4: =COUNTIFS(Cards!$A$2:$A$249,$A4,Cards!$B$2:$B$249,E$2) -> 5 | F4: =COUNTIFS(Cards!$A$2:$A$249,$A4,Cards!$B$2:$B$249,F$2) -> 4 | G4: =COUNTIFS(Cards!$A$2:$A$249,$A4,Cards!$B$2:$B$249,G$2) -> 4
A5: renaissance | B5: =COUNTIFS(Cards!$A$2:$A$249,$A5,Cards!$B$2:$B$249,B$2) -> 9 | C5: =COUNTIFS(Cards!$A$2:$A$249,$A5,Cards!$B$2:$B$249,C$2) -> 4 | D5: =COUNTIFS(Cards!$A$2:$A$249,$A5,Cards!$B$2:$B$249,D$2) -> 4 | E5: =COUNTIFS(Cards!$A$2:$A$249,$A5,Cards!$B$2:$B$249,E$2) -> 5 | F5: =COUNTIFS(Cards!$A$2:$A$249,$A5,Cards!$B$2:$B$249,F$2) -> 4 | G5: =COUNTIFS(Cards!$A$2:$A$249,$A5,Cards!$B$2:$B$249,G$2) -> 4
A6: earlymodern | B6: =COUNTIFS(Cards!$A$2:$A$249,$A6,Cards!$B$2:$B$249,B$2) -> 8 | C6: =COUNTIFS(Cards!$A$2:$A$249,$A6,Cards!$B$2:$B$249,C$2) -> 6 | D6: =COUNTIFS(Cards!$A$2:$A$249,$A6,Cards!$B$2:$B$249,D$2) -> 4 | E6: =COUNTIFS(Cards!$A$2:$A$249,$A6,Cards!$B$2:$B$249,E$2) -> 5 | F6: =COUNTIFS(Cards!$A$2:$A$249,$A6,Cards!$B$2:$B$249,F$2) -> 4 | G6: =COUNTIFS(Cards!$A$2:$A$249,$A6,Cards!$B$2:$B$249,G$2) -> 6
A7: industrial | B7: =COUNTIFS(Cards!$A$2:$A$249,$A7,Cards!$B$2:$B$249,B$2) -> 6 | C7: =COUNTIFS(Cards!$A$2:$A$249,$A7,Cards!$B$2:$B$249,C$2) -> 4 | D7: =COUNTIFS(Cards!$A$2:$A$249,$A7,Cards!$B$2:$B$249,D$2) -> 4 | E7: =COUNTIFS(Cards!$A$2:$A$249,$A7,Cards!$B$2:$B$249,E$2) -> 4 | F7: =COUNTIFS(Cards!$A$2:$A$249,$A7,Cards!$B$2:$B$249,F$2) -> 4 | G7: =COUNTIFS(Cards!$A$2:$A$249,$A7,Cards!$B$2:$B$249,G$2) -> 6
A8: early20 | B8: =COUNTIFS(Cards!$A$2:$A$249,$A8,Cards!$B$2:$B$249,B$2) -> 7 | C8: =COUNTIFS(Cards!$A$2:$A$249,$A8,Cards!$B$2:$B$249,C$2) -> 5 | D8: =COUNTIFS(Cards!$A$2:$A$249,$A8,Cards!$B$2:$B$249,D$2) -> 4 | E8: =COUNTIFS(Cards!$A$2:$A$249,$A8,Cards!$B$2:$B$249,E$2) -> 4 | F8: =COUNTIFS(Cards!$A$2:$A$249,$A8,Cards!$B$2:$B$249,F$2) -> 4 | G8: =COUNTIFS(Cards!$A$2:$A$249,$A8,Cards!$B$2:$B$249,G$2) -> 6
A9: postwar | B9: =COUNTIFS(Cards!$A$2:$A$249,$A9,Cards!$B$2:$B$249,B$2) -> 7 | C9: =COUNTIFS(Cards!$A$2:$A$249,$A9,Cards!$B$2:$B$249,C$2) -> 5 | D9: =COUNTIFS(Cards!$A$2:$A$249,$A9,Cards!$B$2:$B$249,D$2) -> 4 | E9: =COUNTIFS(Cards!$A$2:$A$249,$A9,Cards!$B$2:$B$249,E$2) -> 4 | F9: =COUNTIFS(Cards!$A$2:$A$249,$A9,Cards!$B$2:$B$249,F$2) -> 4 | G9: =COUNTIFS(Cards!$A$2:$A$249,$A9,Cards!$B$2:$B$249,G$2) -> 7
A10: contemporary | B10: =COUNTIFS(Cards!$A$2:$A$249,$A10,Cards!$B$2:$B$249,B$2) -> 9 | C10: =COUNTIFS(Cards!$A$2:$A$249,$A10,Cards!$B$2:$B$249,C$2) -> 6 | D10: =COUNTIFS(Cards!$A$2:$A$249,$A10,Cards!$B$2:$B$249,D$2) -> 6 | E10: =COUNTIFS(Cards!$A$2:$A$249,$A10,Cards!$B$2:$B$249,E$2) -> 5 | F10: =COUNTIFS(Cards!$A$2:$A$249,$A10,Cards!$B$2:$B$249,F$2) -> 5 | G10: =COUNTIFS(Cards!$A$2:$A$249,$A10,Cards!$B$2:$B$249,G$2) -> 9

Sheet EraLeaders
A1: Highest rating per attribute within each era (audit: does the leader deserve it?)
A2: era | B2: Scale | C2: Wealth | D2: Culture | E2: Knowledge | F2: Might
A3: ancient | B3: =SUMPRODUCT(MAX((Cards!$A$2:$A$249=$A3)*Cards!$E$2:$E$249)) -> 97 | C3: =SUMPRODUCT(MAX((Cards!$A$2:$A$249=$A3)*Cards!$F$2:$F$249)) -> 93 | D3: =SUMPRODUCT(MAX((Cards!$A$2:$A$249=$A3)*Cards!$G$2:$G$249)) -> 96 | E3: =SUMPRODUCT(MAX((Cards!$A$2:$A$249=$A3)*Cards!$H$2:$H$249)) -> 99 | F3: =SUMPRODUCT(MAX((Cards!$A$2:$A$249=$A3)*Cards!$I$2:$I$249)) -> 99
A4: medieval | B4: =SUMPRODUCT(MAX((Cards!$A$2:$A$249=$A4)*Cards!$E$2:$E$249)) -> 99 | C4: =SUMPRODUCT(MAX((Cards!$A$2:$A$249=$A4)*Cards!$F$2:$F$249)) -> 96 | D4: =SUMPRODUCT(MAX((Cards!$A$2:$A$249=$A4)*Cards!$G$2:$G$249)) -> 93 | E4: =SUMPRODUCT(MAX((Cards!$A$2:$A$249=$A4)*Cards!$H$2:$H$249)) -> 99 | F4: =SUMPRODUCT(MAX((Cards!$A$2:$A$249=$A4)*Cards!$I$2:$I$249)) -> 95
A5: renaissance | B5: =SUMPRODUCT(MAX((Cards!$A$2:$A$249=$A5)*Cards!$E$2:$E$249)) -> 98 | C5: =SUMPRODUCT(MAX((Cards!$A$2:$A$249=$A5)*Cards!$F$2:$F$249)) -> 97 | D5: =SUMPRODUCT(MAX((Cards!$A$2:$A$249=$A5)*Cards!$G$2:$G$249)) -> 99 | E5: =SUMPRODUCT(MAX((Cards!$A$2:$A$249=$A5)*Cards!$H$2:$H$249)) -> 93 | F5: =SUMPRODUCT(MAX((Cards!$A$2:$A$249=$A5)*Cards!$I$2:$I$249)) -> 97
A6: earlymodern | B6: =SUMPRODUCT(MAX((Cards!$A$2:$A$249=$A6)*Cards!$E$2:$E$249)) -> 99 | C6: =SUMPRODUCT(MAX((Cards!$A$2:$A$249=$A6)*Cards!$F$2:$F$249)) -> 99 | D6: =SUMPRODUCT(MAX((Cards!$A$2:$A$249=$A6)*Cards!$G$2:$G$249)) -> 97 | E6: =SUMPRODUCT(MAX((Cards!$A$2:$A$249=$A6)*Cards!$H$2:$H$249)) -> 96 | F6: =SUMPRODUCT(MAX((Cards!$A$2:$A$249=$A6)*Cards!$I$2:$I$249)) -> 95
A7: industrial | B7: =SUMPRODUCT(MAX((Cards!$A$2:$A$249=$A7)*Cards!$E$2:$E$249)) -> 99 | C7: =SUMPRODUCT(MAX((Cards!$A$2:$A$249=$A7)*Cards!$F$2:$F$249)) -> 99 | D7: =SUMPRODUCT(MAX((Cards!$A$2:$A$249=$A7)*Cards!$G$2:$G$249)) -> 99 | E7: =SUMPRODUCT(MAX((Cards!$A$2:$A$249=$A7)*Cards!$H$2:$H$249)) -> 96 | F7: =SUMPRODUCT(MAX((Cards!$A$2:$A$249=$A7)*Cards!$I$2:$I$249)) -> 99
A8: early20 | B8: =SUMPRODUCT(MAX((Cards!$A$2:$A$249=$A8)*Cards!$E$2:$E$249)) -> 99 | C8: =SUMPRODUCT(MAX((Cards!$A$2:$A$249=$A8)*Cards!$F$2:$F$249)) -> 99 | D8: =SUMPRODUCT(MAX((Cards!$A$2:$A$249=$A8)*Cards!$G$2:$G$249)) -> 99 | E8: =SUMPRODUCT(MAX((Cards!$A$2:$A$249=$A8)*Cards!$H$2:$H$249)) -> 98 | F8: =SUMPRODUCT(MAX((Cards!$A$2:$A$249=$A8)*Cards!$I$2:$I$249)) -> 96
A9: postwar | B9: =SUMPRODUCT(MAX((Cards!$A$2:$A$249=$A9)*Cards!$E$2:$E$249)) -> 99 | C9: =SUMPRODUCT(MAX((Cards!$A$2:$A$249=$A9)*Cards!$F$2:$F$249)) -> 99 | D9: =SUMPRODUCT(MAX((Cards!$A$2:$A$249=$A9)*Cards!$G$2:$G$249)) -> 99 | E9: =SUMPRODUCT(MAX((Cards!$A$2:$A$249=$A9)*Cards!$H$2:$H$249)) -> 95 | F9: =SUMPRODUCT(MAX((Cards!$A$2:$A$249=$A9)*Cards!$I$2:$I$249)) -> 97
A10: contemporary | B10: =SUMPRODUCT(MAX((Cards!$A$2:$A$249=$A10)*Cards!$E$2:$E$249)) -> 99 | C10: =SUMPRODUCT(MAX((Cards!$A$2:$A$249=$A10)*Cards!$F$2:$F$249)) -> 99 | D10: =SUMPRODUCT(MAX((Cards!$A$2:$A$249=$A10)*Cards!$G$2:$G$249)) -> 97 | E10: =SUMPRODUCT(MAX((Cards!$A$2:$A$249=$A10)*Cards!$H$2:$H$249)) -> 99 | F10: =SUMPRODUCT(MAX((Cards!$A$2:$A$249=$A10)*Cards!$I$2:$I$249)) -> 96
